h5_to_json
